[
	{
		"name": "id",
		"dbType": "increments",
		"htmlType": null,
		"validations": null,
		"searchable": false,
		"fillable": false,
		"primary": true,
		"inForm": false,
		"inIndex": false,
		"inView": false
	},
	{
		"name": "user_id",
		"dbType": "string",
		"htmlType": "text",
		"validations": "required",
		"searchable": true,
		"fillable": true,
		"primary": false,
		"inForm": true,
		"inIndex": true,
		"inView": true
	},
	{
		"name": "temp1_day1_before",
		"dbType": "string",
		"htmlType": "text",
		"validations": "required",
		"searchable": true,
		"fillable": true,
		"primary": false,
		"inForm": true,
		"inIndex": true,
		"inView": true
	},
	{
		"name": "temp1_day1_after",
		"dbType": "string",
		"htmlType": "text",
		"validations": "required",
		"searchable": true,
		"fillable": true,
		"primary": false,
		"inForm": true,
		"inIndex": true,
		"inView": true
	},
	{
		"name": "temp1_day2_before",
		"dbType": "string",
		"htmlType": "text",
		"validations": "required",
		"searchable": true,
		"fillable": true,
		"primary": false,
		"inForm": true,
		"inIndex": true,
		"inView": true
	},
	{
		"name": "temp1_day3_after",
		"dbType": "string",
		"htmlType": "text",
		"validations": "required",
		"searchable": true,
		"fillable": true,
		"primary": false,
		"inForm": true,
		"inIndex": true,
		"inView": true
	}
]
